parallel_doctest/__init__.py
parallel_doctest/__main__.py
parallel_doctest/details.py
parallel_doctest/directives.py
parallel_doctest/parallel_doctest.py
parallel_doctest-0.0.2.dist-info/licenses/LICENCE
parallel_doctest-0.0.2.dist-info/METADATA
parallel_doctest-0.0.2.dist-info/WHEEL
parallel_doctest-0.0.2.dist-info/top_level.txt
parallel_doctest-0.0.2.dist-info/RECORD
