Metadata-Version: 2.4
Name: parallel-doctest
Version: 0.0.2
Summary: A replacement/wrapper around doctest to allow tests to be run in parallel
Author-email: David Woods <dw-git@d-woods.co.uk>
License-Expression: MIT
Project-URL: Homepage, https://github.com/da-woods/parallel_doctest
Project-URL: Issues, https://github.com/da-woods/parallel_doctest/issues
Classifier: Programming Language :: Python :: 3
Classifier: Topic :: Software Development :: Testing
Classifier: Operating System :: OS Independent
Requires-Python: >=3.10
License-File: LICENCE
Dynamic: license-file
